{
  "kind": "collectionType",
  "collectionName": "game_servers",
  "info": {
    "name": "GameServer",
    "description": ""
  },
  "options": {
    "increments": true,
    "timestamps": true,
    "draftAndPublish": false
  },
  "attributes": {
    "public_ip": {
      "type": "string",
      "required": true
    },
    "dns": {
      "type": "string",
      "required": true
    },
    "game_config": {
      "via": "game_servers",
      "model": "game-config"
    },
    "private_ip": {
      "type": "string",
      "required": true
    }
  }
}
